petal_qgc_mission_server-0.1.3.dist-info/METADATA
petal_qgc_mission_server-0.1.3.dist-info/WHEEL
petal_qgc_mission_server-0.1.3.dist-info/entry_points.txt
petal_qgc_mission_server/__init__.py
petal_qgc_mission_server/adapter_state.py
petal_qgc_mission_server/config.py
petal_qgc_mission_server/connection.py
petal_qgc_mission_server/core/__init__.py
petal_qgc_mission_server/core/altitude.py
petal_qgc_mission_server/core/converter.py
petal_qgc_mission_server/core/geo.py
petal_qgc_mission_server/core/ned.py
petal_qgc_mission_server/core/state.py
petal_qgc_mission_server/docs/mission_state_architecture.md
petal_qgc_mission_server/docs/reference.md
petal_qgc_mission_server/handlers/__init__.py
petal_qgc_mission_server/handlers/bridge.py
petal_qgc_mission_server/handlers/command.py
petal_qgc_mission_server/handlers/gps.py
petal_qgc_mission_server/handlers/mode.py
petal_qgc_mission_server/handlers/parameter.py
petal_qgc_mission_server/handlers/router.py
petal_qgc_mission_server/mavlink_server.py
petal_qgc_mission_server/mission/__init__.py
petal_qgc_mission_server/mission/download.py
petal_qgc_mission_server/mission/fence_rally.py
petal_qgc_mission_server/mission/mavlink_helpers.py
petal_qgc_mission_server/mission/models.py
petal_qgc_mission_server/mission/storage.py
petal_qgc_mission_server/mission/translation.py
petal_qgc_mission_server/mission/upload.py
petal_qgc_mission_server/mission/utils.py
petal_qgc_mission_server/mission_handler.py
petal_qgc_mission_server/mission_translator.py
petal_qgc_mission_server/plugin.py
petal_qgc_mission_server/resources/current_mission.json
petal_qgc_mission_server/resources/current_mission.waypoints
petal_qgc_mission_server/resources/example_mission.waypoints
petal_qgc_mission_server/resources/last_petal_mission.json
petal_qgc_mission_server/resources/last_petal_mission_curl.sh
petal_qgc_mission_server/resources/last_petal_mission_message.json
petal_qgc_mission_server/resources/test_debug.sh
petal_qgc_mission_server/resources/test_mission_curl.sh
petal_qgc_mission_server/resources/test_single_wp.sh
petal_qgc_mission_server-0.1.3.dist-info/RECORD
