Metadata-Version: 2.1
Name: petal-qgc-mission-server
Version: 0.1.3
Summary: QGC Mission Server
Author-Email: Yaser Othman <yaser.othman@droneleaf.io>
License: MIT
Requires-Python: >=3.10
Requires-Dist: pymavlink>=2.4.37
